tflibs/__init__.py
tflibs/image.py
tflibs/model.py
tflibs/session.py
tflibs/datasets/__init__.py
tflibs/datasets/dataset.py
tflibs/datasets/feature_spec.py
tflibs/datasets/input_pipeline.py
tflibs/nn/__init__.py
tflibs/nn/layers.py
tflibs/ops/__init__.py
tflibs/ops/image.py
tflibs/ops/random.py
tflibs/runner/__init__.py
tflibs/runner/initializer.py
tflibs/runner/runner.py
tflibs/training/__init__.py
tflibs/training/dispatcher.py
tflibs/training/hooks.py
tflibs/training/optimizer.py
tflibs/utils/__init__.py
tflibs/utils/data_structure.py
tflibs/utils/decorators.py
tflibs/utils/device_setter.py
tflibs/utils/ioio.py
tflibs/utils/logging.py
tflibs/utils/pkg.py
tflibs/utils/summary.py
tflibs-0.11.4.dist-info/METADATA
tflibs-0.11.4.dist-info/WHEEL
tflibs-0.11.4.dist-info/top_level.txt
tflibs-0.11.4.dist-info/RECORD
