Metadata-Version: 2.1
Name: tflibs
Version: 0.11.4
Summary: Libraries for easy bootstrapping TensorFlow project
Home-page: https://github.com/shygiants/tflibs
Author: Sanghoon Yoon
Author-email: shygiants@gmail.com
License: UNKNOWN
Keywords: tensorflow,libraries
Platform: UNKNOWN
Classifier: Programming Language :: Python :: 3
Classifier: Programming Language :: Python :: 3.2
Classifier: Programming Language :: Python :: 3.3
Classifier: Programming Language :: Python :: 3.4
Classifier: Programming Language :: Python :: 3.5
Classifier: Programming Language :: Python :: 3.6
Classifier: Programming Language :: Python :: 3.7
Classifier: Programming Language :: Python :: 2.7
Requires-Python: >=2.7
Requires-Dist: wheel
Requires-Dist: tqdm
Requires-Dist: opencv-python
Requires-Dist: requests
Requires-Dist: pandas
Provides-Extra: dev
Requires-Dist: tensorflow (==1.13.1) ; extra == 'dev'
